rockAtlas/.DS_Store
rockAtlas/__init__.py
rockAtlas/__version__.py
rockAtlas/astorb.dat.gz
rockAtlas/cl_utils.py
rockAtlas/database.py
rockAtlas/default_settings.yaml
rockAtlas/setup.cfg
rockAtlas/utKit.py
rockAtlas/bookkeeping/.DS_Store
rockAtlas/bookkeeping/__init__.py
rockAtlas/bookkeeping/bookkeeper.py
rockAtlas/bookkeeping/mysql/bookkeeping.sql
rockAtlas/bookkeeping/tests/.DS_Store
rockAtlas/bookkeeping/tests/__init__.py
rockAtlas/bookkeeping/tests/test_bookkeeper.py
rockAtlas/bookkeeping/tests/input/example_settings.yaml
rockAtlas/bookkeeping/tests/output/example_settings.yaml
rockAtlas/commonutils/.DS_Store
rockAtlas/commonutils/__init__.py
rockAtlas/commonutils/getpackagepath.py
rockAtlas/orbital_elements/__init__.py
rockAtlas/orbital_elements/astorb.py
rockAtlas/orbital_elements/tests/__init__.py
rockAtlas/orbital_elements/tests/test_astorb.py
rockAtlas/orbital_elements/tests/input/example_settings.yaml
rockAtlas/orbital_elements/tests/output/example_settings.yaml
rockAtlas/phot/__init__.py
rockAtlas/phot/dophotMatch.py
rockAtlas/phot/download.py
rockAtlas/phot/tests/__init__.py
rockAtlas/phot/tests/test_dophotMatch.py
rockAtlas/phot/tests/test_download.py
rockAtlas/phot/tests/input/example_settings.yaml
rockAtlas/phot/tests/output/example_settings.yaml
rockAtlas/positions/__init__.py
rockAtlas/positions/orbfitPositions.py
rockAtlas/positions/pyephemPositions.py
rockAtlas/positions/tests/__init__.py
rockAtlas/positions/tests/test_orbfitPositions.py
rockAtlas/positions/tests/test_pyephemPositions.py
rockAtlas/positions/tests/input/example_settings.yaml
rockAtlas/positions/tests/output/example_settings.yaml
rockAtlas/tests/.DS_Store
rockAtlas/tests/__init__.py
rockAtlas/tests/test_database.py
rockAtlas/tests/input/example_settings.yaml
rockAtlas/tests/output/example_settings.yaml
rockAtlas-0.2.3.dist-info/DESCRIPTION.rst
rockAtlas-0.2.3.dist-info/METADATA
rockAtlas-0.2.3.dist-info/RECORD
rockAtlas-0.2.3.dist-info/WHEEL
rockAtlas-0.2.3.dist-info/entry_points.txt
rockAtlas-0.2.3.dist-info/metadata.json
rockAtlas-0.2.3.dist-info/top_level.txt
