Metadata-Version: 2.0
Name: rockAtlas
Version: 0.2.3
Summary: A python package and command-line tools to A suite of tools to pull known solar-system small-body detections out of ATLAS data
Home-page: https://github.com/thespacedoctor/rockAtlas
Author: David Young
Author-email: davidrobertyoung@gmail.com
License: MIT
Download-URL: https://github.com/thespacedoctor/rockAtlas/archive/v0.2.3.zip
Keywords: atlas, asteroid, astronomy
Platform: UNKNOWN
Classifier: Development Status :: 4 - Beta
Classifier: License :: OSI Approved :: MIT License
Classifier: Programming Language :: Python :: 2.7
Classifier: Topic :: Utilities
Requires-Dist: astrocalc
Requires-Dist: fundamentals
Requires-Dist: healpy
Requires-Dist: hmpty
Requires-Dist: pyephem
Requires-Dist: pymysql
Requires-Dist: pyyaml
Requires-Dist: rockAtlas
